roboschool/__init__.py
roboschool/cpp_household.so
roboschool/cpp_household_d.so
roboschool/gym_atlas.py
roboschool/gym_forward_walker.py
roboschool/gym_humanoid_flagrun.py
roboschool/gym_mujoco_walkers.py
roboschool/gym_mujoco_xml_env.py
roboschool/gym_pendulums.py
roboschool/gym_pong.py
roboschool/gym_pong_trainservers.py
roboschool/gym_reacher.py
roboschool/gym_urdf_robot_env.py
roboschool/multiplayer.py
roboschool/random_stadium.py
roboschool/scene_abstract.py
roboschool/scene_stadium.py
roboschool/test_manual.py
roboschool/.libs/Qt3DAnimation
roboschool/.libs/Qt3DCore
roboschool/.libs/Qt3DExtras
roboschool/.libs/Qt3DInput
roboschool/.libs/Qt3DLogic
roboschool/.libs/Qt3DQuick
roboschool/.libs/Qt3DQuickScene2D
roboschool/.libs/Qt3DRender
roboschool/.libs/QtConcurrent
roboschool/.libs/QtCore
roboschool/.libs/QtDBus
roboschool/.libs/QtDesigner
roboschool/.libs/QtGamepad
roboschool/.libs/QtGui
roboschool/.libs/QtLocation
roboschool/.libs/QtMultimedia
roboschool/.libs/QtMultimediaWidgets
roboschool/.libs/QtNetwork
roboschool/.libs/QtOpenGL
roboschool/.libs/QtPositioning
roboschool/.libs/QtPrintSupport
roboschool/.libs/QtQml
roboschool/.libs/QtQuick
roboschool/.libs/QtQuickWidgets
roboschool/.libs/QtSensors
roboschool/.libs/QtSerialBus
roboschool/.libs/QtSerialPort
roboschool/.libs/QtSql
roboschool/.libs/QtSvg
roboschool/.libs/QtTextToSpeech
roboschool/.libs/QtWebChannel
roboschool/.libs/QtWebEngineCore
roboschool/.libs/QtWebEngineWidgets
roboschool/.libs/QtWebSockets
roboschool/.libs/QtWidgets
roboschool/.libs/QtXml
roboschool/.libs/libBullet3Common.2.87.dylib
roboschool/.libs/libBullet3Common.dylib
roboschool/.libs/libBulletCollision.2.87.dylib
roboschool/.libs/libBulletCollision.dylib
roboschool/.libs/libBulletDynamics.2.87.dylib
roboschool/.libs/libBulletDynamics.dylib
roboschool/.libs/libBulletInverseDynamics.2.87.dylib
roboschool/.libs/libBulletInverseDynamics.dylib
roboschool/.libs/libBulletSoftBody.2.87.dylib
roboschool/.libs/libBulletSoftBody.dylib
roboschool-1.0.48.dist-info/LICENSE.md
roboschool-1.0.48.dist-info/METADATA
roboschool-1.0.48.dist-info/WHEEL
roboschool-1.0.48.dist-info/top_level.txt
roboschool-1.0.48.dist-info/RECORD
